setup.py
src/jlddbus/__init__.py
src/jlddbus/do_checks.py
src/jlddbus/do_setup.py
src/jlddbus/script_signal.py
src/jlddbus/tools_sys.py
src/jlddbus.egg-info/PKG-INFO
src/jlddbus.egg-info/SOURCES.txt
src/jlddbus.egg-info/dependency_links.txt
src/jlddbus.egg-info/not-zip-safe
src/jlddbus.egg-info/requires.txt
src/jlddbus.egg-info/top_level.txt
src/scripts/jlddbus-signal