Metadata-Version: 1.0
Name: jlddbus
Version: 0.1
Summary: Collection of DBus related tools
Home-page: UNKNOWN
Author: Jean-Lou Dupont
Author-email: jl@jldupont.com
License: UNKNOWN
Platform: UNKNOWN
